claasp/__init__.py
claasp/cipher.py
claasp/component.py
claasp/compound_xor_differential_cipher.py
claasp/editor.py
claasp/input.py
claasp/name_mappings.py
claasp/round.py
claasp/rounds.py
claasp/DTOs/__init__.py
claasp/DTOs/component_state.py
claasp/DTOs/power_of_2_word_based_dto.py
claasp/cipher_modules/__init__.py
claasp/cipher_modules/algebraic_tests.py
claasp/cipher_modules/avalanche_tests.py
claasp/cipher_modules/code_generator.py
claasp/cipher_modules/component_analysis_tests.py
claasp/cipher_modules/continuous_diffusion_analysis.py
claasp/cipher_modules/division_trail_search.py
claasp/cipher_modules/evaluator.py
claasp/cipher_modules/generic_bit_based_c_functions.c
claasp/cipher_modules/generic_bit_based_c_functions.h
claasp/cipher_modules/generic_functions.py
claasp/cipher_modules/generic_functions_continuous_diffusion_analysis.py
claasp/cipher_modules/generic_functions_vectorized_bit.py
claasp/cipher_modules/generic_functions_vectorized_byte.py
claasp/cipher_modules/generic_word_based_c_functions.c
claasp/cipher_modules/generic_word_based_c_functions.h
claasp/cipher_modules/graph_generator.py
claasp/cipher_modules/inverse_cipher.py
claasp/cipher_modules/neural_network_tests.py
claasp/cipher_modules/report.py
claasp/cipher_modules/tester.py
claasp/cipher_modules/models/__init__.py
claasp/cipher_modules/models/utils.py
claasp/cipher_modules/models/algebraic/__init__.py
claasp/cipher_modules/models/algebraic/algebraic_model.py
claasp/cipher_modules/models/algebraic/boolean_polynomial_ring.py
claasp/cipher_modules/models/algebraic/constraints.py
claasp/cipher_modules/models/cp/__init__.py
claasp/cipher_modules/models/cp/mzn_model.py
claasp/cipher_modules/models/cp/solvers.py
claasp/cipher_modules/models/cp/minizinc_utils/__init__.py
claasp/cipher_modules/models/cp/minizinc_utils/mzn_bct_predicates.py
claasp/cipher_modules/models/cp/minizinc_utils/usefulfunctions.py
claasp/cipher_modules/models/cp/minizinc_utils/utils.py
claasp-4.0.0.dist-info/LICENSE
claasp-4.0.0.dist-info/METADATA
claasp-4.0.0.dist-info/WHEEL
claasp-4.0.0.dist-info/top_level.txt
claasp-4.0.0.dist-info/RECORD
