Metadata-Version: 2.1
Name: claasp
Version: 4.0.0
Summary: CLAASP: Cryptographic Library for Automated Analysis of Symmetric Primitives
Home-page: 
Author: TII Cryptanalysis Team
Author-email: emanuele.bellini@tii.ae
License: GNU General Public License v3.0
Classifier: Development Status :: 4 - Beta
Classifier: Intended Audience :: Science/Research
Classifier: Topic :: Software Development :: Build Tools
Classifier: Topic :: Scientific/Engineering :: Mathematics
Classifier: Programming Language :: Python :: 3
License-File: LICENSE
